mvc_flask/__init__.py
mvc_flask/__version__.py
mvc_flask/helpers/html/input_method_helper.py
mvc_flask/middlewares/blueprint_middleware.py
mvc_flask/middlewares/callback_middleware.py
mvc_flask/middlewares/http/custom_request_middleware.py
mvc_flask/middlewares/http/method_override_middleware.py
mvc_flask/middlewares/http/namespace_middleware.py
mvc_flask/middlewares/http/router_middleware.py
mvc_flask/mvc_flask.py
mvc_flask-2.9.0.dist-info/LICENSE
mvc_flask-2.9.0.dist-info/METADATA
mvc_flask-2.9.0.dist-info/WHEEL
mvc_flask-2.9.0.dist-info/RECORD
