Metadata-Version: 2.1
Name: mvc-flask
Version: 2.9.0
Summary: turn standard Flask into mvc
Home-page: https://github.com/marcuxyz/mvc_flask
License: MIT
Keywords: flask,flask extensions,flask mvc,flask-mvc,mvc flask,flask design pattern
Author: Marcus Pereira
Author-email: marcus@negros.dev
Requires-Python: >=3.8.0,<4.0.0
Classifier: License :: OSI Approved :: MIT License
Classifier: Programming Language :: Python :: 3
Classifier: Programming Language :: Python :: 3.8
Classifier: Programming Language :: Python :: 3.9
Classifier: Programming Language :: Python :: 3.10
Classifier: Programming Language :: Python :: 3.11
Requires-Dist: Flask (==3.0.0)
Requires-Dist: mkdocs-material (>=9.4.8,<10.0.0)
Project-URL: Repository, https://github.com/marcuxyz/mvc_flask
